{
    "__line": 99032,
    "_ancestry": [
        "L_ 11824",
        "B_ {#kzatriyaH#}"
    ],
    "_banner": "{#kzatriyaH#}",
    "_bannerExp": [
        {
            "Right": "kzatriyaH"
        }
    ],
    "_gram": [
        "[{#kzatre rAzwre sADu tasyApatyaM jAtO#}\n{#vA GaH#} <ls>Tv.</ls>]"
    ],
    "_meanings": [
        "A member of the military\nor second caste; {#brAhmaRaH kzatriyo#} \n{#vESyastrayo varRA dvijAtayaH#} <ls>Ms. 10. 4.</ls>\n"
    ],
    "_morphisms": [
        {
            "__line": 99036,
            "_ancestry": [
                "L_ 11824",
                "B_ {#kzatriyaH#}",
                "M_ {#--yaM#}"
            ],
            "_banner": "{#--yaM#}",
            "_bannerExp": [
                {
                    "Right": "kzatriyaM"
                }
            ],
            "_meanings": [
                "The rank or power of the \nKshatriya class. "
            ]
        }
    ],
    "_samasas": [
        {
            "__line": 99037,
            "_ancestry": [
                "L_ 11824",
                "B_ {#kzatriyaH#}",
                "S_  {#--hanaH#}"
            ],
            "_banner": " {#--hanaH#}",
            "_bannerExp": [
                {
                    "Right": "kzatriyahaRaH"
                }
            ],
            "_gram": [
                "({#RaH#})"
            ],
            "_meanings": [
                "an\nepithet of Paraśurāma."
            ]
        }
    ]
}