{
    "__line": 105066,
    "_ancestry": [
        "L_ 12564",
        "B_ {#guRanikA#}"
    ],
    "_banner": "{#guRanikA#}",
    "_bannerExp": [
        {
            "Right": "guRanikA"
        }
    ],
    "_gram": [
        "[{#guR BAve yuc svArTe ka#}]"
    ],
    "_meanings": [
        "{@--1@}\nStudy, repeated reading, repetition;\n{#viSezaviduzaH SAstra yattavodagrAhyate puraH .#} \n{#hetuH paricayasTErye vakturguRanikEva sA ..#}  \n<ls>Śi. 2. 75</ls> ({#AmreqitaM#} <ls>Malli.</ls>). ",
        "{@--2@} Dancing,\nthe science or profession of dancing.\n",
        "{@--3@} The prologue or introduction to\na drama. ",
        "{@--4@} A garland, necklace;\n{#daridrARAM ciMtAmaRiguRanikA#} <ls>Ā. L. 3.</ls> ",
        "{@--5@}\nDetermining the value of the\nvarious readings of a manuscript.\n",
        "{@--6@} A cypher, the character in \narithmetic which expresses nothing."
    ]
}