{
    "__line": 115235,
    "_ancestry": [
        "L_ 13782",
        "B_ {#jaraWa#}"
    ],
    "_banner": "{#jaraWa#}",
    "_bannerExp": [
        {
            "Right": "jaraWa"
        }
    ],
    "_gram": [
        "{%<ab>a.</ab>%}",
        "[{#jF#} {#bA °aWa#}]"
    ],
    "_meanings": [
        "{@--1@} Hard, solid.\n",
        "{@--2@} Old, aged; {#ayamatijaraWAH prakAmagurvIH#}\n{#pariRatadikkarikAstawIrbiBarti#} <ls>Śi. 4. 29</ls>\n(where {#jaraWa#} means ‘hard’ also). ",
        "{@--3@}\nDecayed, decrepit, infirm. ",
        "{@--4@} Bent,\nbowed down, drooping. ",
        "{@--5@} Pale, \nyellowish-white. ",
        "{@--6@} Full-grown, ripe,\nmatured; {#jaraWakamala#} <ls>Śi. 11. 14.</ls> ",
        "{@--7@}\nHard-hearted, cruel. "
    ],
    "_morphisms": [
        {
            "__line": 115243,
            "_ancestry": [
                "L_ 13782",
                "B_ {#jaraWa#}",
                "M_ {#--WaH#}"
            ],
            "_banner": "{#--WaH#}",
            "_bannerExp": [
                {
                    "Right": "jaraWaH"
                }
            ],
            "_meanings": [
                "{@--1@} <ab>N.</ab> of\nPāṇḍu, father of the five Pāṇḍavas.\n",
                "{@--2@} Old age."
            ]
        }
    ]
}