{
    "__line": 123250,
    "_ancestry": [
        "L_ 14851",
        "B_ {#tUryaH, --ryaM#}"
    ],
    "_banner": "{#tUryaH, --ryaM#}",
    "_bannerExp": [
        {
            "Right": "tUryaH"
        },
        {
            "Right": "tUryaM"
        }
    ],
    "_gram": [
        "[{#tUryate tAqyate tUr-yat#}]"
    ],
    "_meanings": [
        "A\nkind of musical instrument;  \n<ls>Ms. 7. 225</ls>; <ls>Ku. 7. 10.</ls> "
    ],
    "_samasas": [
        {
            "__line": 123252,
            "_ancestry": [
                "L_ 14851",
                "B_ {#tUryaH, --ryaM#}",
                "S_  {#--oGaH#}"
            ],
            "_banner": " {#--oGaH#}",
            "_bannerExp": [
                {
                    "Right": "tUryOGaH"
                }
            ],
            "_meanings": [
                "a\nband of instruments. "
            ]
        },
        {
            "__line": 123253,
            "_ancestry": [
                "L_ 14851",
                "B_ {#tUryaH, --ryaM#}",
                "S_ {#--KaMqaH#}"
            ],
            "_banner": "{#--KaMqaH#}",
            "_bannerExp": [
                {
                    "Right": "tUryaKaMqaH"
                }
            ],
            "_meanings": [
                "a sort\nof tabor."
            ]
        }
    ]
}