{
    "__line": 170608,
    "_ancestry": [
        "L_ 20531",
        "B_ {#pramadA#}"
    ],
    "_banner": "{#pramadA#}",
    "_bannerExp": [
        {
            "Right": "pramadA"
        }
    ],
    "_meanings": [
        "{@--1@} A young handsome \nwoman; <ls>R. 9. 31</ls>; <ls>Ś. 5. 17.</ls> ",
        "{@--2@} A\nwife or woman in general;  \n<ls>Ku. 4. 12</ls>; <ls>R. 8. 72.</ls> ",
        "{@--3@} The sign {%virgo%} of\nthe zodiac. "
    ],
    "_samasas": [
        {
            "__line": 170612,
            "_ancestry": [
                "L_ 20531",
                "B_ {#pramadA#}",
                "S_  {#--kAnanaM, --vanaM#}"
            ],
            "_banner": " {#--kAnanaM, --vanaM#}",
            "_bannerExp": [
                {
                    "Right": "pramadAkAnanaM"
                },
                {
                    "Right": "pramadAvanaM"
                }
            ],
            "_meanings": [
                "a\npleasure garden attached to the\nroyal harem (for the use of the\nwives of a king). "
            ]
        },
        {
            "__line": 170615,
            "_ancestry": [
                "L_ 20531",
                "B_ {#pramadA#}",
                "S_ {#--janaH#}"
            ],
            "_banner": "{#--janaH#}",
            "_bannerExp": [
                {
                    "Right": "pramadAjanaH"
                }
            ],
            "_meanings": [
                "{1} a\nyoung woman. ",
                "{2} womankind."
            ]
        }
    ]
}