{
    "__line": 262319,
    "_ancestry": [
        "L_ 31270",
        "B_ {#hayaH#}"
    ],
    "_banner": "{#hayaH#}",
    "_bannerExp": [
        {
            "Right": "hayaH"
        }
    ],
    "_gram": [
        "[{#hay-hi-vA ac#}]"
    ],
    "_meanings": [
        "{@--1@} A horse;  \n<ls>Bg. 1. 14</ls>; <ls>Ms. 8. 296</ls>, <ls>R. 9. 10.</ls> ",
        "{@--2@} A man\nof a particular class; see under\n{#aSva#}. ",
        "{@--3@} The number ‘seven’.\n",
        "{@--4@} <ab>N.</ab> of Indra. ",
        "{@--5@} (In prosody)\nA foot of four short syllables.\n"
    ],
    "_samasas": [
        {
            "__line": 262325,
            "_ancestry": [
                "L_ 31270",
                "B_ {#hayaH#}",
                "S_  {#--aDyakzaH#}"
            ],
            "_banner": " {#--aDyakzaH#}",
            "_bannerExp": [
                {
                    "Right": "hayADyakzaH"
                }
            ],
            "_meanings": [
                "a superintendent\nof horses. "
            ]
        },
        {
            "__line": 262326,
            "_ancestry": [
                "L_ 31270",
                "B_ {#hayaH#}",
                "S_ {#--ariH#}"
            ],
            "_banner": "{#--ariH#}",
            "_bannerExp": [
                {
                    "Right": "hayAriH"
                }
            ],
            "_meanings": [
                "the fragrant \noleander. "
            ]
        },
        {
            "__line": 262327,
            "_ancestry": [
                "L_ 31270",
                "B_ {#hayaH#}",
                "S_ {#--AyurvedaH#}"
            ],
            "_banner": "{#--AyurvedaH#}",
            "_bannerExp": [
                {
                    "Right": "hayAyurvedaH"
                }
            ],
            "_meanings": [
                "veterinary science. \n\n"
            ]
        },
        {
            "__line": 262329,
            "_ancestry": [
                "L_ 31270",
                "B_ {#hayaH#}",
                "S_ {#--ArUQaH#}"
            ],
            "_banner": "{#--ArUQaH#}",
            "_bannerExp": [
                {
                    "Right": "hayArUQaH"
                }
            ],
            "_meanings": [
                "a horseman, rider.  \n"
            ]
        },
        {
            "__line": 262330,
            "_ancestry": [
                "L_ 31270",
                "B_ {#hayaH#}",
                "S_ {#--ArohaH#}"
            ],
            "_banner": "{#--ArohaH#}",
            "_bannerExp": [
                {
                    "Right": "hayArohaH"
                }
            ],
            "_meanings": [
                "{1} a rider. ",
                "{2} riding. "
            ]
        },
        {
            "__line": 262330,
            "_ancestry": [
                "L_ 31270",
                "B_ {#hayaH#}",
                "S_ {#--AsanI#}"
            ],
            "_banner": "{#--AsanI#}",
            "_bannerExp": [
                {
                    "Right": "hayAsanI"
                }
            ],
            "_meanings": [
                "the gum-olibanum tree. "
            ]
        },
        {
            "__line": 262331,
            "_ancestry": [
                "L_ 31270",
                "B_ {#hayaH#}",
                "S_ {#--izwaH#}"
            ],
            "_banner": "{#--izwaH#}",
            "_bannerExp": [
                {
                    "Right": "hayezwaH"
                }
            ],
            "_meanings": [
                "barley. "
            ]
        },
        {
            "__line": 262332,
            "_ancestry": [
                "L_ 31270",
                "B_ {#hayaH#}",
                "S_ {#--uttamaH#}"
            ],
            "_banner": "{#--uttamaH#}",
            "_bannerExp": [
                {
                    "Right": "hayottamaH"
                }
            ],
            "_meanings": [
                "an excellent horse.\n"
            ]
        },
        {
            "__line": 262333,
            "_ancestry": [
                "L_ 31270",
                "B_ {#hayaH#}",
                "S_ {#--kovida#}"
            ],
            "_banner": "{#--kovida#}",
            "_bannerExp": [
                {
                    "Right": "hayakovida"
                }
            ],
            "_gram": [
                "{%<ab>a.</ab>%}"
            ],
            "_meanings": [
                "versed in the science\nof horses-their management, \ntraining &c. "
            ]
        },
        {
            "__line": 262335,
            "_ancestry": [
                "L_ 31270",
                "B_ {#hayaH#}",
                "S_ {#--grIvaH#}"
            ],
            "_banner": "{#--grIvaH#}",
            "_bannerExp": [
                {
                    "Right": "hayagrIvaH"
                }
            ],
            "_meanings": [
                "<ab>N.</ab> of a form\nof Viṣṇu. "
            ],
            "_morphisms": [
                {
                    "__line": 262336,
                    "_ancestry": [
                        "L_ 31270",
                        "B_ {#hayaH#}",
                        "S_ {#--grIvaH#}",
                        "S_M_ ({#--vA#}"
                    ],
                    "_banner": "({#--vA#}",
                    "_bannerExp": [
                        {
                            "Right": "hayagrIvA"
                        }
                    ],
                    "_meanings": [
                        "<ab>N.</ab> of Durgā.\n"
                    ]
                }
            ]
        },
        {
            "__line": 262337,
            "_ancestry": [
                "L_ 31270",
                "B_ {#hayaH#}",
                "S_ {#--jYaH#}"
            ],
            "_banner": "{#--jYaH#}",
            "_bannerExp": [
                {
                    "Right": "hayajYaH"
                }
            ],
            "_meanings": [
                "a horse-dealer, groom, \njockey. "
            ]
        },
        {
            "__line": 262338,
            "_ancestry": [
                "L_ 31270",
                "B_ {#hayaH#}",
                "S_ {#--dvizat#}"
            ],
            "_banner": "{#--dvizat#}",
            "_bannerExp": [
                {
                    "Right": "hayadvizat"
                }
            ],
            "_gram": [
                "{%<ab>m.</ab>%}"
            ],
            "_meanings": [
                "the buffalo. "
            ]
        },
        {
            "__line": 262338,
            "_ancestry": [
                "L_ 31270",
                "B_ {#hayaH#}",
                "S_ {#--priyaH#}"
            ],
            "_banner": "{#--priyaH#}",
            "_bannerExp": [
                {
                    "Right": "hayapriyaH"
                }
            ],
            "_meanings": [
                "barley. "
            ]
        },
        {
            "__line": 262339,
            "_ancestry": [
                "L_ 31270",
                "B_ {#hayaH#}",
                "S_ {#--priyA#}"
            ],
            "_banner": "{#--priyA#}",
            "_bannerExp": [
                {
                    "Right": "hayapriyA"
                }
            ],
            "_meanings": [
                "the {%Kharjūrī%} tree.\n"
            ]
        },
        {
            "__line": 262340,
            "_ancestry": [
                "L_ 31270",
                "B_ {#hayaH#}",
                "S_ {#--mAraH, --mArakaH#}"
            ],
            "_banner": "{#--mAraH, --mArakaH#}",
            "_bannerExp": [
                {
                    "Right": "hayamAraH"
                },
                {
                    "Right": "hayamArakaH"
                }
            ],
            "_meanings": [
                "the fragrant \noleander. "
            ]
        },
        {
            "__line": 262341,
            "_ancestry": [
                "L_ 31270",
                "B_ {#hayaH#}",
                "S_ {#--mAraRaH#}"
            ],
            "_banner": "{#--mAraRaH#}",
            "_bannerExp": [
                {
                    "Right": "hayamAraRaH"
                }
            ],
            "_meanings": [
                "the sacred fig-tree.\n"
            ]
        },
        {
            "__line": 262342,
            "_ancestry": [
                "L_ 31270",
                "B_ {#hayaH#}",
                "S_ {#--meDaH#}"
            ],
            "_banner": "{#--meDaH#}",
            "_bannerExp": [
                {
                    "Right": "hayameDaH"
                }
            ],
            "_meanings": [
                "a horse-sacrifice;  \n<ls>Y. 1. 181.</ls> "
            ]
        },
        {
            "__line": 262343,
            "_ancestry": [
                "L_ 31270",
                "B_ {#hayaH#}",
                "S_ {#--vAhanaH#}"
            ],
            "_banner": "{#--vAhanaH#}",
            "_bannerExp": [
                {
                    "Right": "hayavAhanaH"
                }
            ],
            "_meanings": [
                "an epithet of \nKubera. "
            ]
        },
        {
            "__line": 262344,
            "_ancestry": [
                "L_ 31270",
                "B_ {#hayaH#}",
                "S_ {#--SAlA#}"
            ],
            "_banner": "{#--SAlA#}",
            "_bannerExp": [
                {
                    "Right": "hayaSAlA"
                }
            ],
            "_meanings": [
                "a stable for horses.\n"
            ]
        },
        {
            "__line": 262345,
            "_ancestry": [
                "L_ 31270",
                "B_ {#hayaH#}",
                "S_ {#--SAstraM#}"
            ],
            "_banner": "{#--SAstraM#}",
            "_bannerExp": [
                {
                    "Right": "hayaSAstraM"
                }
            ],
            "_meanings": [
                "the art or science of \ntraining and managing horses. "
            ]
        },
        {
            "__line": 262346,
            "_ancestry": [
                "L_ 31270",
                "B_ {#hayaH#}",
                "S_ {#--saMgrahaRaM#}"
            ],
            "_banner": "{#--saMgrahaRaM#}",
            "_bannerExp": [
                {
                    "Right": "hayasaMgrahaRaM"
                }
            ],
            "_meanings": [
                "the restraining or curbing of horses."
            ]
        }
    ]
}