{
    "__line": 43236,
    "_ancestry": [
        "L_ 4814",
        "B_ {#avaSya#}"
    ],
    "_banner": "{#avaSya#}",
    "_bannerExp": [
        {
            "Right": "avaSya"
        }
    ],
    "_gram": [
        "{%<ab>a.</ab>%}"
    ],
    "_meanings": [
        "{@--1@} Untameable, \nungovernable, unruly. ",
        "{@--2@} Inevitable; {#aTa#}\n{#maraRamavaSyameva jaMtoH#} <ls>Ve. 3. 4.</ls> ",
        "{@--3@}\nIndispensable, necessary. "
    ],
    "_samasas": [
        {
            "__line": 43239,
            "_ancestry": [
                "L_ 4814",
                "B_ {#avaSya#}",
                "S_ \n{#--putraH#}"
            ],
            "_banner": "\n{#--putraH#}",
            "_bannerExp": [
                {
                    "Right": "avaSyaputraH"
                }
            ],
            "_meanings": [
                "a son whom it is impossible\nto govern or teach."
            ]
        }
    ]
}