{
    "__line": 44946,
    "_ancestry": [
        "L_ 5075",
        "B_ {#aviyoga#}"
    ],
    "_banner": "{#aviyoga#}",
    "_bannerExp": [
        {
            "Right": "aviyoga"
        }
    ],
    "_gram": [
        "{%<ab>a.</ab>%}"
    ],
    "_meanings": [
        "Not separated, united,\nconnected. "
    ],
    "_morphisms": [
        {
            "__line": 44947,
            "_ancestry": [
                "L_ 5075",
                "B_ {#aviyoga#}",
                "M_ {#--gaH#}"
            ],
            "_banner": "{#--gaH#}",
            "_bannerExp": [
                {
                    "Right": "aviyogaH"
                }
            ],
            "_meanings": [
                "{@--1@} Non-separation,\npresence. ",
                "{@--2@} Conjunction, \nassociation. "
            ]
        }
    ],
    "_samasas": [
        {
            "__line": 44949,
            "_ancestry": [
                "L_ 5075",
                "B_ {#aviyoga#}",
                "S_  {#--tftIyA#}"
            ],
            "_banner": " {#--tftIyA#}",
            "_bannerExp": [
                {
                    "Right": "aviyogatftIyA"
                }
            ],
            "_meanings": [
                "<ab>N.</ab> of a certain \n\nfestival or holiday. "
            ]
        },
        {
            "__line": 44951,
            "_ancestry": [
                "L_ 5075",
                "B_ {#aviyoga#}",
                "S_ {#--vrataM#}"
            ],
            "_banner": "{#--vrataM#}",
            "_bannerExp": [
                {
                    "Right": "aviyogavrataM"
                }
            ],
            "_meanings": [
                "a vow\nto be observed by women on the\nthird day of the first fortnight of\nMārgaśīrṣa."
            ]
        }
    ]
}