{
    "__line": 45036,
    "_ancestry": [
        "L_ 5089",
        "B_ {#avilaMba#}"
    ],
    "_banner": "{#avilaMba#}",
    "_bannerExp": [
        {
            "Right": "avilaMba"
        }
    ],
    "_gram": [
        "{%<ab>a.</ab>%}"
    ],
    "_meanings": [
        "Prompt, not \ndelaying, quick. "
    ],
    "_morphisms": [
        {
            "__line": 45037,
            "_ancestry": [
                "L_ 5089",
                "B_ {#avilaMba#}",
                "M_ {#--baH#}"
            ],
            "_banner": "{#--baH#}",
            "_bannerExp": [
                {
                    "Right": "avilaMbaH"
                }
            ],
            "_meanings": [
                "Absence of delay,\nquickness, promptitude. "
            ]
        },
        {
            "__line": 45038,
            "_ancestry": [
                "L_ 5089",
                "B_ {#avilaMba#}",
                "M_ {#--baM#}"
            ],
            "_banner": "{#--baM#}",
            "_bannerExp": [
                {
                    "Right": "avilaMbaM"
                }
            ],
            "_meanings": [
                ", \n{#avilaMbena#} {%<ab>ind.</ab>%} Without delay, quickly."
            ]
        }
    ]
}