{
    "__line": 75696,
    "_ancestry": [
        "L_ 8886",
        "B_ {#upavItaM#}"
    ],
    "_banner": "{#upavItaM#}",
    "_bannerExp": [
        {
            "Right": "upavItaM"
        }
    ],
    "_gram": [
        "[{#upa-ve-kta#}]"
    ],
    "_meanings": [
        "{@--1@} Investiture\nwith the sacred thread. ",
        "{@--2@} The\nsacred thread worn by the first\nthree classes of the Hindus;  \n{#pitryamaMSamupavItalakzaRaM mAtfkaM ca DanrUrjitaM#}\n{#daDat#} <ls>R. 11. 64</ls>; {#muktAyajYopavItAni#}  \n<ls>Ku. 6. 6</ls>; <ls>Śi. 1. 7</ls>; <ls>Ki. 12. 23</ls>;  \n<ls>Ms. 2. 44</ls>, <ls n=\"Ms. 2.\">64</ls>, <ls n=\"Ms.\">4. 36</ls>, <ls n=\"Ms. 4.\">66.</ls>"
    ]
}