{
    "__line": 245232,
    "_ancestry": [
        "L_ 29210",
        "B_ {#sanna#}"
    ],
    "_banner": "{#sanna#}",
    "_bannerExp": [
        {
            "Right": "sanna"
        }
    ],
    "_gram": [
        "{%<ab>p. p.</ab>%}",
        "[{#sad-kta#}]"
    ],
    "_meanings": [
        "{@--1@} Sitting\ndown, settling down, lying. ",
        "{@--2@} \nDejected, sunk down, downcast. ",
        "{@--3@}\nDrooping, relaxed; <ls>Ku. 3. 51.</ls> ",
        "{@--4@}\nWeak, low, feeble. ",
        "{@--5@} Wasted \naway, decayed. ",
        "{@--6@} Perished, \ndestroyed. ",
        "{@--7@} Still, motionless. ",
        "{@--8@} Shrunk.\n",
        "{@--9@} Adjacent, near. ",
        "{@--10@} Gone, \ndeparted. ",
        "{@--11@} Sunk, low (in tone &c).\n"
    ],
    "_morphisms": [
        {
            "__line": 245241,
            "_ancestry": [
                "L_ 29210",
                "B_ {#sanna#}",
                "M_ {#--nnaH#}"
            ],
            "_banner": "{#--nnaH#}",
            "_bannerExp": [
                {
                    "Right": "sannaH"
                }
            ],
            "_meanings": [
                "The tree called {#piyAla#}. "
            ]
        },
        {
            "__line": 245241,
            "_ancestry": [
                "L_ 29210",
                "B_ {#sanna#}",
                "M_ {#--nnaM#}"
            ],
            "_banner": "{#--nnaM#}",
            "_bannerExp": [
                {
                    "Right": "sannaM"
                }
            ],
            "_meanings": [
                "A\nlittle, a small quantity. "
            ]
        }
    ],
    "_samasas": [
        {
            "__line": 245242,
            "_ancestry": [
                "L_ 29210",
                "B_ {#sanna#}",
                "S_ \n{#--kaMWa#}"
            ],
            "_banner": "\n{#--kaMWa#}",
            "_bannerExp": [
                {
                    "Right": "sannakaMWa"
                }
            ],
            "_gram": [
                "{%<ab>a.</ab>%}"
            ],
            "_meanings": [
                "choked. "
            ]
        },
        {
            "__line": 245243,
            "_ancestry": [
                "L_ 29210",
                "B_ {#sanna#}",
                "S_ {#--harza#}"
            ],
            "_banner": "{#--harza#}",
            "_bannerExp": [
                {
                    "Right": "sannaharza"
                }
            ],
            "_gram": [
                "{%<ab>a.</ab>%}"
            ],
            "_meanings": [
                "desponding,\ncheerless."
            ]
        }
    ]
}