{
    "__line": 111691,
    "_ancestry": [
        "L_ 13305",
        "B_ {#cikura#}"
    ],
    "_banner": "{#cikura#}",
    "_bannerExp": [
        {
            "Right": "cikura"
        }
    ],
    "_gram": [
        "{%<ab>a.</ab>%}"
    ],
    "_meanings": [
        "{@--1@} Moving, tremulous,\nfickle, unsteady. ",
        "{@--2@} Inconsiderate,\nrash. "
    ],
    "_morphisms": [
        {
            "__line": 111693,
            "_ancestry": [
                "L_ 13305",
                "B_ {#cikura#}",
                "M_ {#--raH#}"
            ],
            "_banner": "{#--raH#}",
            "_bannerExp": [
                {
                    "Right": "cikuraH"
                }
            ],
            "_meanings": [
                "{@--1@} The hair of the head; {#mama#}\n{#rucire cikure kuru mAnada…kusumAni#}  \n<ls>Gīt. 12</ls>; so {#Ganacayarucire racayati cikure#} \n{#taralitataruRAnane#} <ls n=\"Gīt.\">7.</ls> ",
                "{@--2@} A mountain. ",
                "{@--3@}\nA musk-rat. ",
                "{@--4@} A reptile, snake.\n"
            ]
        }
    ],
    "_samasas": [
        {
            "__line": 111698,
            "_ancestry": [
                "L_ 13305",
                "B_ {#cikura#}",
                "S_  {#--uccayaH, --kalApaH, --nikaraH#},\n{#--pakzaH, --pASaH, --BAraH, --hastaH#}"
            ],
            "_banner": " {#--uccayaH, --kalApaH, --nikaraH#},\n{#--pakzaH, --pASaH, --BAraH, --hastaH#}",
            "_bannerExp": [
                {
                    "Right": "cikuraBAraH"
                },
                {
                    "Right": "cikurahastaH"
                },
                {
                    "Right": "cikurakalApaH"
                },
                {
                    "Right": "cikuranikaraH"
                },
                {
                    "Right": "cikurapASaH"
                },
                {
                    "Right": "cikurapakzaH"
                },
                {
                    "Right": "cikuroccayaH"
                }
            ],
            "_meanings": [
                "a mass or\ntuft of hair; {#yasyAScoraScikuranikaraH#}\n{#karRapUro mayUraH#} <ls>P. R. 1. 22.</ls>"
            ]
        }
    ]
}