{
    "__line": 120051,
    "_ancestry": [
        "L_ 14394",
        "B_ {#tapana#}"
    ],
    "_banner": "{#tapana#}",
    "_bannerExp": [
        {
            "Right": "tapana"
        }
    ],
    "_gram": [
        "{%<ab>a.</ab>%}",
        "[{#tap-lyu#}]"
    ],
    "_meanings": [
        "{@--1@} Warming,\nheating, burning, shining &c. ",
        "{@--2@}\nCausing distress, paining. ",
        "{@--3@} The\nsun; {#pratApAttapano yaTA#} <ls>R. 4. 12</ls>;  \n{#lalAwaMtapastapati tapanaH#} <ls>U. 6</ls>; <ls>Māl. 1.</ls> ",
        "{@--4@}\nThe hot season. ",
        "{@--5@} The sun-stone. ",
        "{@--6@}\n<ab>N.</ab> of a hell. ",
        "{@--7@} An epithet of Śiva. ",
        "{@--8@}\nThe Arka plant. ",
        "{@--9@} <ab>N.</ab> of Agastya.\n"
    ],
    "_morphisms": [
        {
            "__line": 120059,
            "_ancestry": [
                "L_ 14394",
                "B_ {#tapana#}",
                "M_ {#--naM#}"
            ],
            "_banner": "{#--naM#}",
            "_bannerExp": [
                {
                    "Right": "tapanaM"
                }
            ],
            "_meanings": [
                "{@--1@} Heat, burning. ",
                "{@--2@} Paining,\ngrieving. ",
                "{@--3@} Mental agony, anguish.\n"
            ]
        }
    ],
    "_samasas": [
        {
            "__line": 120061,
            "_ancestry": [
                "L_ 14394",
                "B_ {#tapana#}",
                "S_  {#--aMSuH, --karaH, --dIDitiH#}"
            ],
            "_banner": " {#--aMSuH, --karaH, --dIDitiH#}",
            "_bannerExp": [
                {
                    "Right": "tapanAMSuH"
                },
                {
                    "Right": "tapanadIDitiH"
                },
                {
                    "Right": "tapanakaraH"
                }
            ],
            "_meanings": [
                "{1} the\nsun. ",
                "{2} a sun-beam. "
            ]
        },
        {
            "__line": 120062,
            "_ancestry": [
                "L_ 14394",
                "B_ {#tapana#}",
                "S_ {#--AtmajaH, --tanayaH#}"
            ],
            "_banner": "{#--AtmajaH, --tanayaH#}",
            "_bannerExp": [
                {
                    "Left": "S error: midAlign tanayaH AtanayaH"
                },
                {
                    "Right": "tapanAtmajaH"
                }
            ],
            "_meanings": [
                "an epithet (1) of Yama. (2) of Karṇa.\n(3) of Sugrīva. "
            ]
        },
        {
            "__line": 120064,
            "_ancestry": [
                "L_ 14394",
                "B_ {#tapana#}",
                "S_ {#--AtmajA, --tanayA#}"
            ],
            "_banner": "{#--AtmajA, --tanayA#}",
            "_bannerExp": [
                {
                    "Left": "S error: midAlign tanayA AtanayA"
                },
                {
                    "Right": "tapanAtmajA"
                }
            ],
            "_meanings": [
                "an epithet of the Yamunā and of the\nGodāvarī. "
            ]
        },
        {
            "__line": 120066,
            "_ancestry": [
                "L_ 14394",
                "B_ {#tapana#}",
                "S_ {#--izwaM#}"
            ],
            "_banner": "{#--izwaM#}",
            "_bannerExp": [
                {
                    "Right": "tapanezwaM"
                }
            ],
            "_meanings": [
                "copper. "
            ]
        },
        {
            "__line": 120066,
            "_ancestry": [
                "L_ 14394",
                "B_ {#tapana#}",
                "S_ {#--upalaH#},\n{#--maRiH#}"
            ],
            "_banner": "{#--upalaH#},\n{#--maRiH#}",
            "_bannerExp": [
                {
                    "Right": "tapanamaRiH"
                },
                {
                    "Right": "tapanopalaH"
                }
            ],
            "_meanings": [
                "the sun-stone. "
            ]
        },
        {
            "__line": 120067,
            "_ancestry": [
                "L_ 14394",
                "B_ {#tapana#}",
                "S_ {#--CadaH#}"
            ],
            "_banner": "{#--CadaH#}",
            "_bannerExp": [
                {
                    "Right": "tapanacCadaH"
                }
            ],
            "_meanings": [
                "the\nsun-flower."
            ]
        }
    ]
}