{
    "__line": 192994,
    "_ancestry": [
        "L_ 22928",
        "B_ {#mAMqalika#}"
    ],
    "_banner": "{#mAMqalika#}",
    "_bannerExp": [
        {
            "Right": "mAMqalikI"
        },
        {
            "Right": "mAMqalika"
        }
    ],
    "_gram": [
        "{%<ab>a.</ab>%}",
        "({#kI#}|{%<ab>f.</ab>%})"
    ],
    "_meanings": [
        "Relating\nto, or ruling, a province. "
    ],
    "_morphisms": [
        {
            "__line": 192995,
            "_ancestry": [
                "L_ 22928",
                "B_ {#mAMqalika#}",
                "M_ {#--kaH#}"
            ],
            "_banner": "{#--kaH#}",
            "_bannerExp": [
                {
                    "Right": "mAMqalikaH"
                }
            ],
            "_meanings": [
                "The\nruler of a province."
            ]
        }
    ]
}