{
    "__line": 34880,
    "_ancestry": [
        "L_ 3845",
        "B_ {#amUrta#}"
    ],
    "_banner": "{#amUrta#}",
    "_bannerExp": [
        {
            "Right": "amUrta"
        }
    ],
    "_gram": [
        "{%<ab>a.</ab>%}"
    ],
    "_meanings": [
        "Formless, shapeless, \nincorporeal, unembodied (<ab>opp.</ab> {#mUrta#}\nwhere <ls>Muktā.</ls> says {#mUrtatvaM#} = \n{#avacCinnaparimARavattvaM#}). "
    ],
    "_morphisms": [
        {
            "__line": 34883,
            "_ancestry": [
                "L_ 3845",
                "B_ {#amUrta#}",
                "M_ {#--rtaH#}"
            ],
            "_banner": "{#--rtaH#}",
            "_bannerExp": [
                {
                    "Right": "amUrtaH"
                }
            ],
            "_meanings": [
                "<ab>N.</ab> of Śiva. "
            ]
        }
    ],
    "_samasas": [
        {
            "__line": 34883,
            "_ancestry": [
                "L_ 3845",
                "B_ {#amUrta#}",
                "S_ \n{#--guRaH#}"
            ],
            "_banner": "\n{#--guRaH#}",
            "_bannerExp": [
                {
                    "Right": "amUrtaguRaH"
                }
            ],
            "_meanings": [
                "(In <ls>Vaiś.</ls> <ab>phil.</ab>) a quality\nconsidered to be {#amUrta#} or incorporeal\nsuch as {#Darma, aDarma#} &c.; {#DarmADarmO BAvanA#}\n{#ca Sabdo budDyAdayopi ca . ete'mUrtaguRAH sarve#}\nBhāṣa <lbinfo n=\"ls:P.+\"/>"
            ]
        }
    ]
}