{
    "__line": 50103,
    "_ancestry": [
        "L_ 5686",
        "B_ {#ahi#}"
    ],
    "_banner": "{#ahi#}",
    "_bannerExp": [
        {
            "Right": "ahi"
        }
    ],
    "_gram": [
        "{%<ab>a.</ab>%}"
    ],
    "_meanings": [
        "Killing; pervaded, \npervading. "
    ],
    "_morphisms": [
        {
            "__line": 50104,
            "_ancestry": [
                "L_ 5686",
                "B_ {#ahi#}",
                "M_ {#--hiH#}"
            ],
            "_banner": "{#--hiH#}",
            "_bannerExp": [
                {
                    "Right": "ahiH"
                }
            ],
            "_gram": [
                "[{#AhaMti, A-hana-iRa sa ca#}\n{#qit ANo TasvaSca#} <ls>Uṇ. 4. 137</ls>]"
            ],
            "_meanings": [
                "{@--1@} A\nserpent, snake; {#ahayaH savizAH sarve#} \n\n{#nirvizA quMqumAH smftAH#} <ls>Ks. 14. 84.</ls> ",
                "{@--2@}\nThe sun. ",
                "{@--3@} The planet Rāhu. ",
                "{@--4@} A\ntraveller. ",
                "{@--5@} The demon Vṛtra. ",
                "{@--6@}\nA wicked man. ",
                "{@--7@} A cheat, rogue.\n",
                "{@--8@} The Aśleṣā Nakṣatra. ",
                "{@--9@}\nWater. ",
                "{@--10@} Earth. ",
                "{@--11@} A milch\ncow. ",
                "{@--12@} Lead. ",
                "{@--13@} The navel. ",
                "{@--14@}\nA cloud. "
            ]
        },
        {
            "__line": 50115,
            "_ancestry": [
                "L_ 5686",
                "B_ {#ahi#}",
                "M_ {#--hI#}"
            ],
            "_banner": "{#--hI#}",
            "_bannerExp": [
                {
                    "Right": "ahI"
                }
            ],
            "_meanings": [
                "(<ab>du.</ab>) Heaven and\nearth. [<ab>cf.</ab>, <ab>L.</ab> {%anguis%}, <ab>Gr.</ab> {%ehis%}].\n"
            ]
        }
    ],
    "_samasas": [
        {
            "__line": 50117,
            "_ancestry": [
                "L_ 5686",
                "B_ {#ahi#}",
                "S_  {#--arzu#}"
            ],
            "_banner": " {#--arzu#}",
            "_bannerExp": [
                {
                    "Right": "ahyarzu"
                }
            ],
            "_gram": [
                "{%<ab>a.</ab>%}"
            ],
            "_meanings": [
                "gliding away like\na snake, not facing the enemy.\n"
            ]
        },
        {
            "__line": 50119,
            "_ancestry": [
                "L_ 5686",
                "B_ {#ahi#}",
                "S_ {#--kAMtaH#}"
            ],
            "_banner": "{#--kAMtaH#}",
            "_bannerExp": [
                {
                    "Right": "ahikAMtaH"
                }
            ],
            "_meanings": [
                "air, wind. "
            ]
        },
        {
            "__line": 50119,
            "_ancestry": [
                "L_ 5686",
                "B_ {#ahi#}",
                "S_ {#--kozaH#}"
            ],
            "_banner": "{#--kozaH#}",
            "_bannerExp": [
                {
                    "Right": "ahikozaH"
                }
            ],
            "_meanings": [
                "the slough\nof a snake. "
            ]
        },
        {
            "__line": 50120,
            "_ancestry": [
                "L_ 5686",
                "B_ {#ahi#}",
                "S_ {#--kzatraH, --kzetraH#}"
            ],
            "_banner": "{#--kzatraH, --kzetraH#}",
            "_bannerExp": [
                {
                    "Right": "ahikzatraH"
                },
                {
                    "Right": "ahikzetraH"
                }
            ],
            "_meanings": [
                "<ab>N.</ab> of a\ncountry in the east. "
            ]
        },
        {
            "__line": 50121,
            "_ancestry": [
                "L_ 5686",
                "B_ {#ahi#}",
                "S_ {#--gopa#}"
            ],
            "_banner": "{#--gopa#}",
            "_bannerExp": [
                {
                    "Right": "ahigopa"
                }
            ],
            "_gram": [
                "{%<ab>a.</ab>%}"
            ],
            "_meanings": [
                "<ab>Ved.</ab>\nguarded by a serpent. "
            ]
        },
        {
            "__line": 50122,
            "_ancestry": [
                "L_ 5686",
                "B_ {#ahi#}",
                "S_ {#--GnaM#}"
            ],
            "_banner": "{#--GnaM#}",
            "_bannerExp": [
                {
                    "Right": "ahiGnaM"
                }
            ],
            "_meanings": [
                "the \nslaying of the serpent or demon Vṛtra.\n"
            ]
        },
        {
            "__line": 50124,
            "_ancestry": [
                "L_ 5686",
                "B_ {#ahi#}",
                "S_ {#--GnI#}"
            ],
            "_banner": "{#--GnI#}",
            "_bannerExp": [
                {
                    "Right": "ahiGnI"
                }
            ],
            "_gram": [
                "{%<ab>m.</ab>%}"
            ],
            "_meanings": [
                "killing snakes. "
            ]
        },
        {
            "__line": 50124,
            "_ancestry": [
                "L_ 5686",
                "B_ {#ahi#}",
                "S_ {#--CatraH#}"
            ],
            "_banner": "{#--CatraH#}",
            "_bannerExp": [
                {
                    "Right": "ahicCatraH"
                }
            ],
            "_meanings": [
                "{1} <ab>N.</ab>\nof a country, conquered by Arjuna\nand given to Droṇa. ",
                "{2} a kind of\nvegetable poison. "
            ],
            "_morphisms": [
                {
                    "__line": 50127,
                    "_ancestry": [
                        "L_ 5686",
                        "B_ {#ahi#}",
                        "S_ {#--CatraH#}",
                        "S_M_ ({#--trA#}"
                    ],
                    "_banner": "({#--trA#}",
                    "_bannerExp": [
                        {
                            "Right": "ahicCatrA"
                        }
                    ],
                    "_meanings": [
                        "{1} sugar.\n",
                        "{2} the plant {#mezaSfMgI#}. ",
                        "{3} <ab>N.</ab> of the\ncity {#ahicCatra#}. "
                    ]
                }
            ]
        },
        {
            "__line": 50129,
            "_ancestry": [
                "L_ 5686",
                "B_ {#ahi#}",
                "S_ {#--CatrakaM#}"
            ],
            "_banner": "{#--CatrakaM#}",
            "_bannerExp": [
                {
                    "Right": "ahicCatrakaM"
                }
            ],
            "_meanings": [
                "a mushroom.\n"
            ]
        },
        {
            "__line": 50130,
            "_ancestry": [
                "L_ 5686",
                "B_ {#ahi#}",
                "S_ {#--jit#}"
            ],
            "_banner": "{#--jit#}",
            "_bannerExp": [
                {
                    "Right": "ahijit"
                }
            ],
            "_gram": [
                "{%<ab>m.</ab>%}"
            ],
            "_meanings": [
                "{1} <ab>N.</ab> of Kṛṣṇa (the\nslayer of the serpent Kāliya). ",
                "{2}\n<ab>N.</ab> of Indra. "
            ]
        },
        {
            "__line": 50132,
            "_ancestry": [
                "L_ 5686",
                "B_ {#ahi#}",
                "S_ {#--jihvA#}"
            ],
            "_banner": "{#--jihvA#}",
            "_bannerExp": [
                {
                    "Right": "ahijihvA"
                }
            ],
            "_meanings": [
                "<ab>N.</ab> of a plant\n({#nAgajihvAlatA#}). "
            ]
        },
        {
            "__line": 50133,
            "_ancestry": [
                "L_ 5686",
                "B_ {#ahi#}",
                "S_ {#--tuMqikaH#}"
            ],
            "_banner": "{#--tuMqikaH#}",
            "_bannerExp": [
                {
                    "Right": "ahituMqikaH"
                }
            ],
            "_gram": [
                "[{#ahestuMqaM muKaM#}\n{#tena dIvyati Wan, WaY vA#}]"
            ],
            "_meanings": [
                "a \nsnake-catcher, conjurer, juggler. "
            ]
        },
        {
            "__line": 50135,
            "_ancestry": [
                "L_ 5686",
                "B_ {#ahi#}",
                "S_ {#--dviz, --druh#},\n{#--mAra, --ripu, --vidviz#}"
            ],
            "_banner": "{#--dviz, --druh#},\n{#--mAra, --ripu, --vidviz#}",
            "_bannerExp": [
                {
                    "Left": "S error: midAlign ripu mAripu"
                },
                {
                    "Right": "ahidruh"
                },
                {
                    "Right": "ahidviz"
                },
                {
                    "Right": "ahimAra"
                },
                {
                    "Right": "ahividviz"
                }
            ],
            "_gram": [
                "{%<ab>m.</ab>%}"
            ],
            "_meanings": [
                "{1} <ab>N.</ab> of Garuḍa.\n",
                "{2} an ichneumon. ",
                "{3} a peacock.\n",
                "{4} Indra. ",
                "{5} Kṛṣṇa; <ls>Ki. 4. 27</ls>;\n<ls>Śi. 1. 41.</ls> "
            ]
        },
        {
            "__line": 50139,
            "_ancestry": [
                "L_ 5686",
                "B_ {#ahi#}",
                "S_ {#--nakulaM#}"
            ],
            "_banner": "{#--nakulaM#}",
            "_bannerExp": [
                {
                    "Right": "ahinakulaM"
                }
            ],
            "_meanings": [
                "snakes and \nichneumons. "
            ]
        },
        {
            "__line": 50140,
            "_ancestry": [
                "L_ 5686",
                "B_ {#ahi#}",
                "S_ {#--nakulikA#}"
            ],
            "_banner": "{#--nakulikA#}",
            "_bannerExp": [
                {
                    "Right": "ahinakulikA"
                }
            ],
            "_gram": [
                "[{#ahinakulayorvEram#}\n{#vun#} <ls>P. II. 4. 9</ls>]"
            ],
            "_meanings": [
                "the natural \nantipathy between a serpent and an \nichneumon. "
            ]
        },
        {
            "__line": 50143,
            "_ancestry": [
                "L_ 5686",
                "B_ {#ahi#}",
                "S_ {#--nAmaBft#}"
            ],
            "_banner": "{#--nAmaBft#}",
            "_bannerExp": [
                {
                    "Right": "ahinAmaBft"
                }
            ],
            "_gram": [
                "{%<ab>m.</ab>%}"
            ],
            "_meanings": [
                "<ab>N.</ab> of Baladeva.\n"
            ]
        },
        {
            "__line": 50144,
            "_ancestry": [
                "L_ 5686",
                "B_ {#ahi#}",
                "S_ {#--nirmokaH, --nivlayanI#}"
            ],
            "_banner": "{#--nirmokaH, --nivlayanI#}",
            "_bannerExp": [
                {
                    "Right": "ahinirmokaH"
                },
                {
                    "Right": "ahinivlayanI"
                }
            ],
            "_meanings": [
                "the slough of a\nsnake. "
            ]
        },
        {
            "__line": 50145,
            "_ancestry": [
                "L_ 5686",
                "B_ {#ahi#}",
                "S_ {#--patAkaH#}"
            ],
            "_banner": "{#--patAkaH#}",
            "_bannerExp": [
                {
                    "Right": "ahipatAkaH"
                }
            ],
            "_meanings": [
                "a kind of snake\n(not venomous). "
            ]
        },
        {
            "__line": 50146,
            "_ancestry": [
                "L_ 5686",
                "B_ {#ahi#}",
                "S_ {#--patiH#}"
            ],
            "_banner": "{#--patiH#}",
            "_bannerExp": [
                {
                    "Right": "ahipatiH"
                }
            ],
            "_meanings": [
                "{1} ‘the lord\nof snakes’, Vāsuki. ",
                "{2} any large\nserpent. "
            ]
        },
        {
            "__line": 50148,
            "_ancestry": [
                "L_ 5686",
                "B_ {#ahi#}",
                "S_ {#--putrakaH#}"
            ],
            "_banner": "{#--putrakaH#}",
            "_bannerExp": [
                {
                    "Right": "ahiputrakaH"
                }
            ],
            "_meanings": [
                "a kind of boat \n(serpent-shaped). "
            ]
        },
        {
            "__line": 50149,
            "_ancestry": [
                "L_ 5686",
                "B_ {#ahi#}",
                "S_ {#--pUtanaM, --nA#}"
            ],
            "_banner": "{#--pUtanaM, --nA#}",
            "_bannerExp": [
                {
                    "Right": "ahipUtanA"
                },
                {
                    "Right": "ahipUtanaM"
                }
            ],
            "_meanings": [
                "a kind of\ndisease. "
            ]
        },
        {
            "__line": 50150,
            "_ancestry": [
                "L_ 5686",
                "B_ {#ahi#}",
                "S_ {#--PenaH --naM#}"
            ],
            "_banner": "{#--PenaH --naM#}",
            "_bannerExp": [
                {
                    "Right": "ahiPenaH"
                },
                {
                    "Right": "ahiPenaM"
                }
            ],
            "_meanings": [
                "‘the saliva or \nvenom of a snake’, opium. "
            ]
        },
        {
            "__line": 50151,
            "_ancestry": [
                "L_ 5686",
                "B_ {#ahi#}",
                "S_ {#--bu (vu) DnaH#},\n{#--vraDnaH, ahirbuDnaH --DnyaH#}"
            ],
            "_banner": "{#--bu (vu) DnaH#},\n{#--vraDnaH, ahirbuDnaH --DnyaH#}",
            "_bannerExp": [
                {
                    "Left": "Parser error: {#ahi#} S_ {#--bu (vu) DnaH#},\n{#--vraDnaH, ahirbuDnaH --DnyaH#}"
                }
            ],
            "_meanings": [
                "{1} one of the\nRudras. ",
                "{2} Śiva. ",
                "{3} \nUttarābhādrapadā Nakṣatra. ",
                "{4} a name of a\nMuhūrta. "
            ],
            "_samasas": [
                {
                    "__line": 50155,
                    "_ancestry": [
                        "L_ 5686",
                        "B_ {#ahi#}",
                        "S_ {#--bu (vu) DnaH#},\n{#--vraDnaH, ahirbuDnaH --DnyaH#}",
                        "S_S_ {#°devatA#}"
                    ],
                    "_banner": "{#°devatA#}",
                    "_meanings": [
                        "the twenty-sixth\nlunar mansion. "
                    ]
                }
            ]
        },
        {
            "__line": 50156,
            "_ancestry": [
                "L_ 5686",
                "B_ {#ahi#}",
                "S_ {#--BayaM#}"
            ],
            "_banner": "{#--BayaM#}",
            "_bannerExp": [
                {
                    "Right": "ahiBayaM"
                }
            ],
            "_meanings": [
                "{1} the fear of\na lurking snake. ",
                "{2} apprehension\nof treachery, danger arising from\none's own allies; "
            ],
            "_samasas": [
                {
                    "__line": 50159,
                    "_ancestry": [
                        "L_ 5686",
                        "B_ {#ahi#}",
                        "S_ {#--BayaM#}",
                        "S_S_ {#°dA#}"
                    ],
                    "_banner": "{#°dA#}",
                    "_bannerExp": [
                        {
                            "Right": "ahiBayadA"
                        }
                    ],
                    "_meanings": [
                        "[{#ahiM BayaM dyati#} \n{#KaMqayati do ka#}] <ab>N.</ab> of the plant {#BUmyAmalakI#}.\n"
                    ]
                }
            ]
        },
        {
            "__line": 50161,
            "_ancestry": [
                "L_ 5686",
                "B_ {#ahi#}",
                "S_ {#--BAnu#}"
            ],
            "_banner": "{#--BAnu#}",
            "_bannerExp": [
                {
                    "Right": "ahiBAnu"
                }
            ],
            "_gram": [
                "{%<ab>a.</ab>%}"
            ],
            "_meanings": [
                "<ab>Ved.</ab> ",
                "{1} shining like\nserpents. ",
                "{2} causing the motion of\nthe sun ({#sUryagatihetu#}) as the wind;\nan epithet of the Maruts. "
            ]
        },
        {
            "__line": 50164,
            "_ancestry": [
                "L_ 5686",
                "B_ {#ahi#}",
                "S_ {#--Buj#}"
            ],
            "_banner": "{#--Buj#}",
            "_bannerExp": [
                {
                    "Right": "ahiBuj"
                }
            ],
            "_gram": [
                "{%<ab>m.</ab>%}"
            ],
            "_meanings": [
                "{1} <ab>N.</ab> of Garuḍa. ",
                "{2} a peacock. ",
                "{3} \n\nichneumon. ",
                "{4} <ab>N.</ab> of a plant. "
            ]
        },
        {
            "__line": 50167,
            "_ancestry": [
                "L_ 5686",
                "B_ {#ahi#}",
                "S_ {#--Bft#}"
            ],
            "_banner": "{#--Bft#}",
            "_bannerExp": [
                {
                    "Right": "ahiBft"
                }
            ],
            "_gram": [
                "{%<ab>m.</ab>%}"
            ],
            "_meanings": [
                "Śiva. "
            ]
        },
        {
            "__line": 50168,
            "_ancestry": [
                "L_ 5686",
                "B_ {#ahi#}",
                "S_ {#--manyu#}"
            ],
            "_banner": "{#--manyu#}",
            "_bannerExp": [
                {
                    "Right": "ahimanyu"
                }
            ],
            "_gram": [
                "{%<ab>a.</ab>%}"
            ],
            "_meanings": [
                "{1} having \ndestructive anger or with unimpaired\nknowledge. ",
                "{2} enraged like \nserpents; epithet of the Maruts. "
            ],
            "_morphisms": [
                {
                    "__line": 50171,
                    "_ancestry": [
                        "L_ 5686",
                        "B_ {#ahi#}",
                        "S_ {#--manyu#}",
                        "S_M_ ({#--nyuH#}"
                    ],
                    "_banner": "({#--nyuH#}",
                    "_bannerExp": [
                        {
                            "Right": "ahimanyuH"
                        }
                    ],
                    "_meanings": [
                        "the anger of a serpent. "
                    ]
                }
            ]
        },
        {
            "__line": 50172,
            "_ancestry": [
                "L_ 5686",
                "B_ {#ahi#}",
                "S_ {#--mardanI#}"
            ],
            "_banner": "{#--mardanI#}",
            "_bannerExp": [
                {
                    "Right": "ahimardanI"
                }
            ],
            "_meanings": [
                "<ab>N.</ab>\nof a plant ({#gaMDanAkulI#}). "
            ]
        },
        {
            "__line": 50173,
            "_ancestry": [
                "L_ 5686",
                "B_ {#ahi#}",
                "S_ {#--mAya#}"
            ],
            "_banner": "{#--mAya#}",
            "_bannerExp": [
                {
                    "Right": "ahimAya"
                }
            ],
            "_gram": [
                "{%<ab>a.</ab>%}"
            ],
            "_meanings": [
                "having multiform or versatile forms\nlike a snake, showing a variety of\ncolour and shape, such as Vṛtra.\n"
            ]
        },
        {
            "__line": 50177,
            "_ancestry": [
                "L_ 5686",
                "B_ {#ahi#}",
                "S_ {#--mArakaH, --medakaH#}"
            ],
            "_banner": "{#--mArakaH, --medakaH#}",
            "_bannerExp": [
                {
                    "Right": "ahimArakaH"
                },
                {
                    "Right": "ahimedakaH"
                }
            ],
            "_meanings": [
                "{1} <ab>N.</ab> of a plant\n({#arimeda#}). ",
                "{2} = {#°dviz#} <ab>q. v.</ab> "
            ]
        },
        {
            "__line": 50178,
            "_ancestry": [
                "L_ 5686",
                "B_ {#ahi#}",
                "S_ {#--latA#}"
            ],
            "_banner": "{#--latA#}",
            "_bannerExp": [
                {
                    "Right": "ahilatA"
                }
            ],
            "_meanings": [
                "{1}\nthe betel-nut plant. ",
                "{2} <ab>N.</ab> of a\nplant ({#gaMDanAkulI#}.) "
            ]
        },
        {
            "__line": 50180,
            "_ancestry": [
                "L_ 5686",
                "B_ {#ahi#}",
                "S_ {#--Suzma#}"
            ],
            "_banner": "{#--Suzma#}",
            "_bannerExp": [
                {
                    "Right": "ahiSuzma"
                }
            ],
            "_gram": [
                "{%<ab>a.</ab>%}"
            ],
            "_meanings": [
                "having\nall-pervading strength; "
            ],
            "_samasas": [
                {
                    "__line": 50181,
                    "_ancestry": [
                        "L_ 5686",
                        "B_ {#ahi#}",
                        "S_ {#--Suzma#}",
                        "S_S_ {#°satvan#}"
                    ],
                    "_banner": "{#°satvan#}",
                    "_bannerExp": [
                        {
                            "Right": "ahiSuzmasatvan"
                        }
                    ],
                    "_meanings": [
                        "<ab>Ved.</ab>\none whose men hiss like serpents.\n"
                    ]
                }
            ]
        },
        {
            "__line": 50183,
            "_ancestry": [
                "L_ 5686",
                "B_ {#ahi#}",
                "S_ {#--sakTa#}"
            ],
            "_banner": "{#--sakTa#}",
            "_bannerExp": [
                {
                    "Right": "ahisakTa"
                }
            ],
            "_gram": [
                "{%<ab>a.</ab>%}"
            ],
            "_meanings": [
                "having a long thigh like\na serpent. "
            ],
            "_morphisms": [
                {
                    "__line": 50184,
                    "_ancestry": [
                        "L_ 5686",
                        "B_ {#ahi#}",
                        "S_ {#--sakTa#}",
                        "S_M_ ({#--kTaH#}"
                    ],
                    "_banner": "({#--kTaH#}",
                    "_bannerExp": [
                        {
                            "Right": "ahisakTaH"
                        }
                    ],
                    "_meanings": [
                        "<ab>N.</ab> of a country.\n"
                    ]
                }
            ]
        },
        {
            "__line": 50185,
            "_ancestry": [
                "L_ 5686",
                "B_ {#ahi#}",
                "S_ {#--hatyaM#}"
            ],
            "_banner": "{#--hatyaM#}",
            "_bannerExp": [
                {
                    "Right": "ahihatyaM"
                }
            ],
            "_meanings": [
                "<ab>Ved.</ab> the slaying of the \nserpent or demon Vṛtra. "
            ]
        },
        {
            "__line": 50186,
            "_ancestry": [
                "L_ 5686",
                "B_ {#ahi#}",
                "S_ {#--han#}"
            ],
            "_banner": "{#--han#}",
            "_bannerExp": [
                {
                    "Right": "ahihan"
                }
            ],
            "_gram": [
                "{%<ab>a.</ab>%}"
            ],
            "_meanings": [
                "killing serpents or Vṛtra, Garuḍa,\nIndra."
            ]
        }
    ]
}