{
    "__line": 52776,
    "_ancestry": [
        "L_ 5998",
        "B_ {#AjAnaH#}"
    ],
    "_banner": "{#AjAnaH#}",
    "_bannerExp": [
        {
            "Right": "AjAnaH"
        }
    ],
    "_gram": [
        "[{#A-jan-GaY#}]"
    ],
    "_meanings": [
        "{@--1@} Birth, \norigin. ",
        "{@--2@} Generating cause (said to be\n{%<ab>n.</ab>%} also in these two senses). "
    ],
    "_morphisms": [
        {
            "__line": 52778,
            "_ancestry": [
                "L_ 5998",
                "B_ {#AjAnaH#}",
                "M_ {#--naM#}"
            ],
            "_banner": "{#--naM#}",
            "_bannerExp": [
                {
                    "Right": "AjAnaM"
                }
            ],
            "_meanings": [
                "{@--1@}\nBirth-place. ",
                "{@--2@} Birth, descent, species\n(<ab>Ved.</ab>). "
            ]
        },
        {
            "__line": 52780,
            "_ancestry": [
                "L_ 5998",
                "B_ {#AjAnaH#}",
                "M_ {%--<ab>ind.</ab>%}"
            ],
            "_bannerExp": [
                {
                    "Right": "AjAnaH"
                }
            ],
            "_gram": [
                "{%--<ab>ind.</ab>%}"
            ],
            "_meanings": [
                "From the time of the\ncreation. "
            ]
        }
    ],
    "_samasas": [
        {
            "__line": 52781,
            "_ancestry": [
                "L_ 5998",
                "B_ {#AjAnaH#}",
                "S_  {#--ja#}"
            ],
            "_banner": " {#--ja#}",
            "_bannerExp": [
                {
                    "Right": "AjAnaja"
                }
            ],
            "_gram": [
                "{%<ab>a.</ab>%}"
            ],
            "_meanings": [
                "born since\nthe creation (as gods &c). "
            ]
        },
        {
            "__line": 52782,
            "_ancestry": [
                "L_ 5998",
                "B_ {#AjAnaH#}",
                "S_ {#--devaH#}"
            ],
            "_banner": "{#--devaH#}",
            "_bannerExp": [
                {
                    "Right": "AjAnadevaH"
                }
            ],
            "_meanings": [
                "a\ngod from the very creation."
            ]
        }
    ]
}